{"resourceTypeCapabilities":[{"resourceType":{"id":"user","displayName":"User","traits":["TRAIT_USER"],"description":"JumpCloud User: The User account is the core identity for your employees, and is the account type that is used to authenticate resources agains"},"capabilities":["CAPABILITY_SYNC"]},{"resourceType":{"id":"group","displayName":"Group","traits":["TRAIT_GROUP"]},"capabilities":["CAPABILITY_SYNC","CAPABILITY_PROVISION"]},{"resourceType":{"id":"role","displayName":"Role","traits":["TRAIT_ROLE"]},"capabilities":["CAPABILITY_SYNC"]},{"resourceType":{"id":"app","displayName":"App","traits":["TRAIT_APP"]},"capabilities":["CAPABILITY_SYNC"]}]}